[
  {
    "regex": "^An azure icewyrm opens its maw wide before breathing forth a stream of freezing air towards (\\w+).$",
    "args": [
      {
        "GroupAsTarget": 1
      },
      {
        "Literal": "Woodlore"
      },
      {
        "Literal": "Icewyrm"
      },
      {
        "Literal": ""
      },
      {
        "Literal": ""
      }
    ],
    "observation_name": "Proc"
  },
  {
    "regex": "^Your crocodile has afflicted (\\w+) with (\\w+).$",
    "args": [
      {
        "GroupAsTarget": 1
      },
      {
        "Literal": "Woodlore"
      },
      {
        "Literal": "Crocodile"
      },
      {
        "GroupAsTarget": 2
      },
      {
        "Literal": ""
      }
    ],
    "observation_name": "Proc"
  },
  {
    "regex": "^Your cockatrice has afflicted (\\w+) with (\\w+).$",
    "args": [
      {
        "GroupAsTarget": 1
      },
      {
        "Literal": "Woodlore"
      },
      {
        "Literal": "Cockatrice"
      },
      {
        "GroupAsTarget": 2
      },
      {
        "Literal": ""
      }
    ],
    "observation_name": "Proc"
  },
  {
    "regex": "^Your weasel has stripped (\\w+)'s (\\w+) defence.$",
    "args": [
      {
        "GroupAsTarget": 1
      },
      {
        "Literal": "Woodlore"
      },
      {
        "Literal": "Weasel"
      },
      {
        "GroupAsTarget": 2
      },
      {
        "Literal": ""
      }
    ],
    "observation_name": "Proc"
  }
]